PyScrub/__init__.py
PyScrub/data_cleaning.py
PyScrub/data_profiler.py
PyScrub/data_transformation.py
PyScrub/feature_engineering.py
PyScrub/pipeline_integration.py
PyScrub/visualization.py
PyScrub-0.0.1.dist-info/METADATA
PyScrub-0.0.1.dist-info/WHEEL
PyScrub-0.0.1.dist-info/top_level.txt
PyScrub-0.0.1.dist-info/RECORD
