Metadata-Version: 2.1
Name: PyScrub
Version: 0.0.1
Summary: PyScrub is a powerful Python library designed to streamline data preprocessing and pipeline automation. It provides efficient tools for data cleaning, transformation, feature engineering, and visualization, all integrated into a reproducible and scalable pipeline framework.
Author: Fasugba Ayomide
Author-email: Ayomide Fasugba <fasugbapaul@gmail.com>
Project-URL: Homepage, https://github.com/fashjr/PyScrub
Project-URL: Issues, https://github.com/fashjr/PyScrub/issues
Project-URL: Documentation, https://github.com/fashjr/PyScrub/docs
Project-URL: Source, https://github.com/fashjr/PyScrub/source
Keywords: python,data cleaning,data transformation,data pipeline,machine learning,data preprocessing
Classifier: Development Status :: 3 - Alpha
Classifier: Intended Audience :: Developers
Classifier: Intended Audience :: Science/Research
Classifier: Topic :: Software Development :: Libraries :: Python Modules
Classifier: Topic :: Scientific/Engineering :: Information Analysis
Classifier: Programming Language :: Python :: 3
Classifier: Operating System :: OS Independent
Requires-Python: >=3.8
Requires-Dist: pandas
Requires-Dist: numpy
Requires-Dist: matplotlib
Requires-Dist: seaborn
Requires-Dist: scikit-learn
